odoo10_addon_event_contact-10.0.1.0.0-py2.7-nspkg.pth
odoo/addons/event_contact/README.rst
odoo/addons/event_contact/__init__.py
odoo/addons/event_contact/__manifest__.py
odoo/addons/event_contact/i18n/es.po
odoo/addons/event_contact/models/__init__.py
odoo/addons/event_contact/models/event_event.py
odoo/addons/event_contact/models/event_type.py
odoo/addons/event_contact/static/description/icon.png
odoo/addons/event_contact/tests/__init__.py
odoo/addons/event_contact/tests/test_event.py
odoo/addons/event_contact/views/event_event_view.xml
odoo/addons/event_contact/views/event_type_view.xml
odoo10_addon_event_contact-10.0.1.0.0.dist-info/DESCRIPTION.rst
odoo10_addon_event_contact-10.0.1.0.0.dist-info/METADATA
odoo10_addon_event_contact-10.0.1.0.0.dist-info/RECORD
odoo10_addon_event_contact-10.0.1.0.0.dist-info/WHEEL
odoo10_addon_event_contact-10.0.1.0.0.dist-info/metadata.json
odoo10_addon_event_contact-10.0.1.0.0.dist-info/namespace_packages.txt
odoo10_addon_event_contact-10.0.1.0.0.dist-info/top_level.txt
